Workbook

Sheet Assumptions
A1: Tech Startup — Financial Model Assumptions
A3: Revenue
A4: Starting MRR | B4: 420000
A5: Monthly MRR Growth Rate | B5: 0.08
A6: Monthly Churn Rate | B6: 0.025
A7: Starting Customers | B7: 280
A8: ARPU (monthly) | B8: 1500
A10: COSTS & MARGIN
A11: Gross Margin | B11: 0.78
A12: Starting Headcount | B12: 52
A13: Avg Fully-Loaded Cost / Employee (monthly) | B13: 14000
A14: Non-Payroll OpEx (monthly) | B14: 180000
A15: New Hires per Month | B15: 3
A17: CASH
A18: Starting Cash Balance | B18: 11500000
A19: Forecast Months | B19: 24

Sheet Monthly_Forecast
B1: =DATE(2026,1,1) -> 46023 | C1: =EDATE(B1,1) -> 46054 | D1: =EDATE(C1,1) -> 46082 | E1: =EDATE(D1,1) -> 46113 | F1: =EDATE(E1,1) -> 46143 | G1: =EDATE(F1,1) -> 46174 | H1: =EDATE(G1,1) -> 46204 | I1: =EDATE(H1,1) -> 46235 | J1: =EDATE(I1,1) -> 46266 | ... Y1: =EDATE(X1,1) -> 46722
A2: REVENUE
A3: Customers | B3: =Assumptions!B7 -> 280 | C3: =B3*(1+Assumptions!$B$5-Assumptions!$B$6) -> 295.4 | D3: =C3*(1+Assumptions!$B$5-Assumptions!$B$6) -> 311.647 | E3: =D3*(1+Assumptions!$B$5-Assumptions!$B$6) -> 328.78759 | F3: =E3*(1+Assumptions!$B$5-Assumptions!$B$6) -> 346.8709 | G3: =F3*(1+Assumptions!$B$5-Assumptions!$B$6) -> 365.9488 | H3: =G3*(1+Assumptions!$B$5-Assumptions!$B$6) -> 386.07599 | I3: =H3*(1+Assumptions!$B$5-Assumptions!$B$6) -> 407.31017 | J3: =I3*(1+Assumptions!$B$5-Assumptions!$B$6) -> 429.71222 | ... Y3: =X3*(1+Assumptions!$B$5-Assumptions!$B$6) -> 959.32244
A4: MRR | B4: =B3*Assumptions!$B$8 -> 420000 | C4: =C3*Assumptions!$B$8 -> 443100 | D4: =D3*Assumptions!$B$8 -> 467470.5 | E4: =E3*Assumptions!$B$8 -> 493181.38 | F4: =F3*Assumptions!$B$8 -> 520306.35 | G4: =G3*Assumptions!$B$8 -> 548923.2 | H4: =H3*Assumptions!$B$8 -> 579113.98 | I4: =I3*Assumptions!$B$8 -> 610965.25 | ... Y4: =Y3*Assumptions!$B$8 -> 1438983.7
A6: COSTS
A7: Headcount | B7: =Assumptions!B12 -> 52 | C7: =B7+Assumptions!$B$15 -> 55 | D7: =C7+Assumptions!$B$15 -> 58 | E7: =D7+Assumptions!$B$15 -> 61 | F7: =E7+Assumptions!$B$15 -> 64 | G7: =F7+Assumptions!$B$15 -> 67 | H7: =G7+Assumptions!$B$15 -> 70 | I7: =H7+Assumptions!$B$15 -> 73 | J7: =I7+Assumptions!$B$15 -> 76 | ... Y7: =X7+Assumptions!$B$15 -> 121
A8: Payroll Cost | B8: =B7*Assumptions!$B$13 -> 728000 | C8: =C7*Assumptions!$B$13 -> 770000 | D8: =D7*Assumptions!$B$13 -> 812000 | E8: =E7*Assumptions!$B$13 -> 854000 | F8: =F7*Assumptions!$B$13 -> 896000 | G8: =G7*Assumptions!$B$13 -> 938000 | H8: =H7*Assumptions!$B$13 -> 980000 | I8: =I7*Assumptions!$B$13 -> 1022000 | ... Y8: =Y7*Assumptions!$B$13 -> 1694000
A9: Non-Payroll OpEx | B9: =Assumptions!$B$14 -> 180000 | C9: =Assumptions!$B$14 -> 180000 | D9: =Assumptions!$B$14 -> 180000 | E9: =Assumptions!$B$14 -> 180000 | F9: =Assumptions!$B$14 -> 180000 | G9: =Assumptions!$B$14 -> 180000 | H9: =Assumptions!$B$14 -> 180000 | I9: =Assumptions!$B$14 -> 180000 | ... Y9: =Assumptions!$B$14 -> 180000
A10: COGS (Cost of Goods Sold) | B10: =B4*(1-Assumptions!$B$11) -> 92400 | C10: =C4*(1-Assumptions!$B$11) -> 97482 | D10: =D4*(1-Assumptions!$B$11) -> 102843.51 | E10: =E4*(1-Assumptions!$B$11) -> 108499.9 | F10: =F4*(1-Assumptions!$B$11) -> 114467.4 | G10: =G4*(1-Assumptions!$B$11) -> 120763.1 | H10: =H4*(1-Assumptions!$B$11) -> 127405.08 | I10: =I4*(1-Assumptions!$B$11) -> 134412.35 | ... Y10: =Y4*(1-Assumptions!$B$11) -> 316576.4
A12: CASH FLOW
A13: Total Revenue | B13: =B4 -> 420000 | C13: =C4 -> 443100 | D13: =D4 -> 467470.5 | E13: =E4 -> 493181.38 | F13: =F4 -> 520306.35 | G13: =G4 -> 548923.2 | H13: =H4 -> 579113.98 | I13: =I4 -> 610965.25 | ... Y13: =Y4 -> 1438983.7
A14: Total Costs | B14: =B8+B9+B10 -> 1000400 | C14: =C8+C9+C10 -> 1047482 | D14: =D8+D9+D10 -> 1094843.5 | E14: =E8+E9+E10 -> 1142499.9 | F14: =F8+F9+F10 -> 1190467.4 | G14: =G8+G9+G10 -> 1238763.1 | H14: =H8+H9+H10 -> 1287405.1 | I14: =I8+I9+I10 -> 1336412.4 | ... Y14: =Y8+Y9+Y10 -> 2190576.4
A15: Net Burn | B15: =B13-B14 -> -580400 | C15: =C13-C14 -> -604382 | D15: =D13-D14 -> -627373.01 | E15: =E13-E14 -> -649318.53 | F15: =F13-F14 -> -670161.04 | G15: =G13-G14 -> -689839.9 | H15: =H13-H14 -> -708291.1 | I15: =I13-I14 -> -725447.11 | ... Y15: =Y13-Y14 -> -751592.75
A16: Cash Balance | B16: =Assumptions!B18 -> 11500000 | C16: =B16+C15 -> 10895618 | D16: =C16+D15 -> 10268245 | E16: =D16+E15 -> 9618926.5 | F16: =E16+F15 -> 8948765.4 | G16: =F16+G15 -> 8258925.5 | H16: =G16+H15 -> 7550634.4 | I16: =H16+I15 -> 6825187.3 | J16: =I16+J15 -> 6083950.6 | ... Y16: =X16+Y15 -> -5730151.8

Sheet Runway_Analysis
A3: Starting Cash | B3: =Monthly_Forecast!B16 -> 11500000
A4: Current Monthly Burn | B4: =ABS(Monthly_Forecast!B15) -> 580400
A5: Average Monthly Burn | B5: =ABS(AVERAGE(Monthly_Forecast!B15:Y15)) -> 742106.32
A6: Runway — Simple (months) | B6: =B3/B5 -> 15.496432
A8: Cash-Out Month: | B8: Month 14
A9: Cash-Out Date: | B9: March 2027

Sheet Dashboard
