Workbook

Sheet Executive Summary
A2: Executive Summary
A4: Title | B4: Executive Summary – Tech Startup Cash Flow Forecast
A5: Project Context | B5: 12-month cash flow forecast for an early-stage B2B SaaS company. Tracks subscription revenue growth, operating burn, and runway under base-case assumptions.
A6: Objective | B6: Project runway, identify cash-tight months, and surface where additional capital may be needed before reaching break-even.
A7: Method | B7: Driver-based monthly cash flow model with active customer growth driving MRR; fixed and variable operating costs; capital structure with founder equity and venture debt.
A8: Key Insight | B8: Early months show cash dips due to high S&M spend and infrastructure investment; revenue compounds as customer base grows; closing balance trends positive in second half of year.
A9: Tools Used | B9: Excel — driver-based formulas, monthly forecast with sensitivity analysis, KPI dashboard with MRR, ARR, CAC, LTV, and Churn.
A10: Next Steps | B10: Review monthly variance vs forecast; refine churn and CAC assumptions with actual cohort data; extend to multi-year forecast post-product-market-fit.

Sheet Cash Flow Forecasting
A1: B2B SaaS Startup
A2: Cash Flow Forecast 2024
A3: 12-month cash flow projection — subscription revenue, customer growth, operational burn
A5: Date | C5: 45309 | D5: 45341 | E5: 45373 | F5: 45405 | G5: 45437 | H5: 45469 | I5: 45501 | J5: 45533 | K5: 45565 | L5: 45566 | M5: 45599 | N5: 45630 | O5: Total
A7: Cash in-flows
A8: Subscription Revenue (Monthly) | B8: 300 | C8: =+C35 -> 0 | D8: =+$B$8*D35 -> 600 | E8: =+$B$8*E35 -> 1500 | F8: =+$B$8*F35 -> 2400 | G8: =+$B$8*G35 -> 3000 | H8: =+$B$8*H35 -> 3300 | I8: =+$B$8*I35 -> 3900 | J8: =+$B$8*J35 -> 4500 | K8: =+$B$8*K35 -> 5100 | ... N8: =+$B$8*N35 -> 6900 | O8: =+SUM(C8:N8) -> 43200
A9: Venture Debt | C9: 2000 | O9: =+SUM(C9:N9) -> 2000
A10: Founder Capital / Bridge | C10: 2000 | E10: 1000 | O10: =+SUM(C10:N10) -> 3000
A12: Total Cash In-Flows | C12: =+SUM(C8:C10) -> 4000 | D12: =+SUM(D8:D10) -> 600 | E12: =+SUM(E8:E10) -> 2500 | F12: =+SUM(F8:F10) -> 2400 | G12: =+SUM(G8:G10) -> 3000 | H12: =+SUM(H8:H10) -> 3300 | I12: =+SUM(I8:I10) -> 3900 | J12: =+SUM(J8:J10) -> 4500 | ... O12: =+SUM(O8:O10) -> 48200
A14: Cash Out-Flows
A15: Infrastructure CapEx | C15: 750 | E15: 1500 | O15: =SUM(C15:N15) -> 2250
A16: Debt Service | D16: 75 | E16: 75 | F16: 75 | G16: 75 | H16: 75 | I16: 75 | J16: 75 | K16: 75 | L16: 75 | M16: 75 | N16: 75 | O16: =SUM(C16:N16) -> 825
A17: Cloud Hosting (AWS/GCP) | B17: 150 | C17: =+$B$17*C36 -> 2250 | D17: =+$B$17*D36 -> 0 | E17: =+$B$17*E36 -> 0 | F17: =+$B$17*F36 -> 3000 | G17: =+$B$17*G36 -> 3750 | H17: =+$B$17*H36 -> 0 | I17: =+$B$17*I36 -> 4500 | J17: =+$B$17*J36 -> 0 | ... N17: =+$B$17*N36 -> 0 | O17: =SUM(C17:N17) -> 24000
A18: Sales & Marketing | C18: 150 | D18: 150 | E18: 150 | F18: 150 | G18: 150 | H18: 150 | I18: 150 | J18: 150 | K18: 150 | L18: 150 | M18: 150 | N18: 150 | O18: =SUM(C18:N18) -> 1800
A19: Payment Processing Fees | B19: 1.5 | C19: =+$B$19*C35 -> 0 | D19: =+$B$19*D35 -> 3 | E19: =+$B$19*E35 -> 7.5 | F19: =+$B$19*F35 -> 12 | G19: =+$B$19*G35 -> 15 | H19: =+$B$19*H35 -> 16.5 | I19: =+$B$19*I35 -> 19.5 | J19: =+$B$19*J35 -> 22.5 | ... N19: =+$B$19*N35 -> 34.5 | O19: =SUM(C19:N19) -> 216
A20: Customer Support Tools | B20: 5 | C20: =+$B$20*C35 -> 0 | D20: =+$B$20*D35 -> 10 | E20: =+$B$20*E35 -> 25 | F20: =+$B$20*F35 -> 40 | G20: =+$B$20*G35 -> 50 | H20: =+$B$20*H35 -> 55 | I20: =+$B$20*I35 -> 65 | J20: =+$B$20*J35 -> 75 | ... N20: =+$B$20*N35 -> 115 | O20: =SUM(C20:N20) -> 720
A21: Productivity Software | C21: 125 | I21: 50 | O21: =SUM(C21:N21) -> 175
A22: Communication Tools (Slack/Zoom) | C22: 50 | D22: 50 | E22: 50 | F22: 50 | G22: 50 | H22: 50 | I22: 50 | J22: 50 | K22: 50 | L22: 50 | M22: 50 | N22: 50 | O22: =SUM(C22:N22) -> 600
A23: Web Hosting & Domains | C23: 25 | D23: 25 | E23: 25 | F23: 25 | G23: 25 | H23: 25 | I23: 25 | J23: 25 | K23: 25 | L23: 25 | M23: 25 | N23: 25 | O23: =SUM(C23:N23) -> 300
A24: Interest Expense | G24: 10 | I24: 10 | O24: =SUM(C24:N24) -> 20
A25: Founder Salary | F25: 500 | G25: 500 | H25: 500 | I25: 750 | J25: 750 | K25: 750 | L25: 750 | M25: 750 | N25: 750 | O25: =SUM(C25:N25) -> 6000
A27: Total Cash Out-Flows | C27: =SUM(C15:C25) -> 3350 | D27: =SUM(D15:D25) -> 313 | E27: =SUM(E15:E25) -> 1832.5 | F27: =SUM(F15:F25) -> 3852 | G27: =SUM(G15:G25) -> 4625 | H27: =SUM(H15:H25) -> 871.5 | I27: =SUM(I15:I25) -> 5694.5 | J27: =SUM(J15:J25) -> 1147.5 | ... O27: =SUM(O15:O25) -> 36906
A28: Fixed Monthly Burn | C28: =C16+C18+C22+C23+C25 -> 225 | D28: =D16+D18+D22+D23+D25 -> 300 | E28: =E16+E18+E22+E23+E25 -> 300 | F28: =F16+F18+F22+F23+F25 -> 800 | G28: =G16+G18+G22+G23+G25 -> 800 | H28: =H16+H18+H22+H23+H25 -> 800 | I28: =I16+I18+I22+I23+I25 -> 1050 | J28: =J16+J18+J22+J23+J25 -> 1050 | ... O28: =O16+O18+O22+O23+O25 -> 9525
A30: Net Cash Flow | C30: =+C12-C27 -> 650 | D30: =+D12-D27 -> 287 | E30: =+E12-E27 -> 667.5 | F30: =+F12-F27 -> -1452 | G30: =+G12-G27 -> -1625 | H30: =+H12-H27 -> 2428.5 | I30: =+I12-I27 -> -1794.5 | J30: =+J12-J27 -> 3352.5 | ... O30: =+O12-O27 -> 11294
A32: Opening Cash Balance | C32: 0 | D32: =+C33 -> 650 | E32: =+D33 -> 937 | F32: =+E33 -> 1604.5 | G32: =+F33 -> 152.5 | H32: =+G33 -> -1472.5 | I32: =+H33 -> 956 | J32: =+I33 -> -838.5 | K32: =+J33 -> 2514 | ... N32: =+M33 -> 5593.5 | O32: =+C32 -> 0
A33: Closing Cash Balance | C33: =C32+C30 -> 650 | D33: =D32+D30 -> 937 | E33: =E32+E30 -> 1604.5 | F33: =F32+F30 -> 152.5 | G33: =G32+G30 -> -1472.5 | H33: =H32+H30 -> 956 | I33: =I32+I30 -> -838.5 | J33: =J32+J30 -> 2514 | ... O33: =O32+O30 -> 11294
A35: Active Customers (MRR-bearing) | C35: 0 | D35: 2 | E35: 5 | F35: 8 | G35: 10 | H35: 11 | I35: =+H35+2 -> 13 | J35: =+I35+2 -> 15 | K35: =+J35+2 -> 17 | L35: =+K35+2 -> 19 | M35: =+L35+2 -> 21 | N35: =+M35+2 -> 23
A36: Cloud Usage Index | C36: 15 | F36: 20 | G36: 25 | I36: 30 | K36: 40 | M36: 30
A37: Net Customer / Usage Delta | C37: =-C35+C36 -> 15 | D37: =-D35+D36 -> -2 | E37: =-E35+E36 -> -5 | F37: =-F35+F36 -> 12 | G37: =-G35+G36 -> 15 | H37: =-H35+H36 -> -11 | I37: =-I35+I36 -> 17 | J37: =-J35+J36 -> -15 | ... N37: =-N35+N36 -> -23
A38: Cumulative Position | C38: =+C37 -> 15 | D38: =+C38+D37 -> 13 | E38: =+D38+E37 -> 8 | F38: =+E38+F37 -> 20 | G38: =+F38+G37 -> 35 | H38: =+G38+H37 -> 24 | I38: =+H38+I37 -> 41 | J38: =+I38+J37 -> 26 | K38: =+J38+K37 -> 49 | ... N38: =+M38+N37 -> 16
A40: Insight: Cash flow shows tight liquidity through mid-year due to equipment purchases and inventory buildup. Cash position recovers strongly in Q4, suggesting the business is front-loading expenses to capitalize on year-end sales.
A41: Based on the cash flow forecast, the business has approximately four months of runway before requiring additional funding, with liquidity tightening in mid-year due to inventory buildup and capital expenditures.
A42: Fixed monthly burn increases mid-year due to the introduction of recurring owner drawings, which structurally raises the minimum liquidity requirement.”

Sheet SaaS KPIs
A1: SaaS KPIs Dashboard — B2B SaaS Startup
A3: Metric | B3: Assumption | C3: Jan | D3: Feb | E3: Mar | F3: Apr | G3: May | H3: Jun | I3: Jul | J3: Aug | K3: Sep | L3: Oct | M3: Nov | N3: Dec | O3: Year
A5: Customer Drivers
A6: Beginning Customers | C6: 0 | D6: =C10 -> 0 | E6: =D10 -> 2 | F6: =E10 -> 5 | G6: =F10 -> 8 | H6: =G10 -> 10 | I6: =H10 -> 11 | J6: =I10 -> 13 | K6: =J10 -> 15 | ... N6: =M10 -> 21
A7: New Customers Acquired | C7: ='Cash Flow Forecasting'!C35 -> 0 | D7: =MAX('Cash Flow Forecasting'!D35-'Cash Flow Forecasting'!C35+C10*$B$8,0) -> 2 | E7: =MAX('Cash Flow Forecasting'!E35-'Cash Flow Forecasting'!D35+D10*$B$8,0) -> 3.06 | F7: =MAX('Cash Flow Forecasting'!F35-'Cash Flow Forecasting'!E35+E10*$B$8,0) -> 3.15 | G7: =MAX('Cash Flow Forecasting'!G35-'Cash Flow Forecasting'!F35+F10*$B$8,0) -> 2.24 | H7: =MAX('Cash Flow Forecasting'!H35-'Cash Flow Forecasting'!G35+G10*$B$8,0) -> 1.3 | I7: =MAX('Cash Flow Forecasting'!I35-'Cash Flow Forecasting'!H35+H10*$B$8,0) -> 2.33 | J7: =MAX('Cash Flow Forecasting'!J35-'Cash Flow Forecasting'!I35+I10*$B$8,0) -> 2.39 | K7: =MAX('Cash Flow Forecasting'!K35-'Cash Flow Forecasting'!J35+J10*$B$8,0) -> 2.45 | ... N7: =MAX('Cash Flow Forecasting'!N35-'Cash Flow Forecasting'!M35+M10*$B$8,0) -> 2.63
A8: Monthly Churn Rate | B8: 0.03
A9: Churned Customers | C9: =ROUND(C6*$B$8,0) -> 0 | D9: =ROUND(D6*$B$8,0) -> 0 | E9: =ROUND(E6*$B$8,0) -> 0 | F9: =ROUND(F6*$B$8,0) -> 0 | G9: =ROUND(G6*$B$8,0) -> 0 | H9: =ROUND(H6*$B$8,0) -> 0 | I9: =ROUND(I6*$B$8,0) -> 0 | J9: =ROUND(J6*$B$8,0) -> 0 | ... N9: =ROUND(N6*$B$8,0) -> 1
A10: Ending Customers | C10: ='Cash Flow Forecasting'!C35 -> 0 | D10: ='Cash Flow Forecasting'!D35 -> 2 | E10: ='Cash Flow Forecasting'!E35 -> 5 | F10: ='Cash Flow Forecasting'!F35 -> 8 | G10: ='Cash Flow Forecasting'!G35 -> 10 | H10: ='Cash Flow Forecasting'!H35 -> 11 | I10: ='Cash Flow Forecasting'!I35 -> 13 | J10: ='Cash Flow Forecasting'!J35 -> 15 | ... N10: ='Cash Flow Forecasting'!N35 -> 23
A11: Average Customers | C11: =(C6+C10)/2 -> 0 | D11: =(D6+D10)/2 -> 1 | E11: =(E6+E10)/2 -> 3.5 | F11: =(F6+F10)/2 -> 6.5 | G11: =(G6+G10)/2 -> 9 | H11: =(H6+H10)/2 -> 10.5 | I11: =(I6+I10)/2 -> 12 | J11: =(J6+J10)/2 -> 14 | ... N11: =(N6+N10)/2 -> 22
A13: Revenue Metrics (MRR / ARR)
A14: ARPU (Monthly) | B14: $/mo | C14: ='Cash Flow Forecasting'!$B$8 -> 300 | D14: ='Cash Flow Forecasting'!$B$8 -> 300 | E14: ='Cash Flow Forecasting'!$B$8 -> 300 | F14: ='Cash Flow Forecasting'!$B$8 -> 300 | G14: ='Cash Flow Forecasting'!$B$8 -> 300 | H14: ='Cash Flow Forecasting'!$B$8 -> 300 | I14: ='Cash Flow Forecasting'!$B$8 -> 300 | J14: ='Cash Flow Forecasting'!$B$8 -> 300 | ... N14: ='Cash Flow Forecasting'!$B$8 -> 300
A15: MRR (Monthly Recurring Revenue) | C15: =C11*C14 -> 0 | D15: =D11*D14 -> 300 | E15: =E11*E14 -> 1050 | F15: =F11*F14 -> 1950 | G15: =G11*G14 -> 2700 | H15: =H11*H14 -> 3150 | I15: =I11*I14 -> 3600 | J15: =J11*J14 -> 4200 | ... N15: =N11*N14 -> 6600 | O15: =SUM(C15:N15) -> 39750
A16: ARR (Annual Recurring Revenue) | C16: =C10*C14*12 -> 0 | D16: =D10*D14*12 -> 7200 | E16: =E10*E14*12 -> 18000 | F16: =F10*F14*12 -> 28800 | G16: =G10*G14*12 -> 36000 | H16: =H10*H14*12 -> 39600 | I16: =I10*I14*12 -> 46800 | J16: =J10*J14*12 -> 54000 | ... N16: =N10*N14*12 -> 82800
A17: MRR Growth % | D17: =IFERROR(D15/C15-1,0) -> 0 | E17: =IFERROR(E15/D15-1,0) -> 2.5 | F17: =IFERROR(F15/E15-1,0) -> 0.85714286 | G17: =IFERROR(G15/F15-1,0) -> 0.38461538 | H17: =IFERROR(H15/G15-1,0) -> 0.16666667 | I17: =IFERROR(I15/H15-1,0) -> 0.14285714 | J17: =IFERROR(J15/I15-1,0) -> 0.16666667 | K17: =IFERROR(K15/J15-1,0) -> 0.14285714 | ... N17: =IFERROR(N15/M15-1,0) -> 0.1
A19: Unit Economics
A20: S&M Spend | C20: ='Cash Flow Forecasting'!C18 -> 150 | D20: ='Cash Flow Forecasting'!D18 -> 150 | E20: ='Cash Flow Forecasting'!E18 -> 150 | F20: ='Cash Flow Forecasting'!F18 -> 150 | G20: ='Cash Flow Forecasting'!G18 -> 150 | H20: ='Cash Flow Forecasting'!H18 -> 150 | I20: ='Cash Flow Forecasting'!I18 -> 150 | J20: ='Cash Flow Forecasting'!J18 -> 150 | ... N20: ='Cash Flow Forecasting'!N18 -> 150
A21: CAC (Customer Acquisition Cost) | C21: =IFERROR(C20/C7,0) -> 0 | D21: =IFERROR(D20/D7,0) -> 75 | E21: =IFERROR(E20/E7,0) -> 49.019608 | F21: =IFERROR(F20/F7,0) -> 47.619048 | G21: =IFERROR(G20/G7,0) -> 66.964286 | H21: =IFERROR(H20/H7,0) -> 115.38462 | I21: =IFERROR(I20/I7,0) -> 64.377682 | J21: =IFERROR(J20/J7,0) -> 62.761506 | ... N21: =IFERROR(N20/N7,0) -> 57.034221
A22: Gross Margin % | B22: 0.75
A23: LTV (Lifetime Value) | C23: =IFERROR(C14*$B$22/$B$8,0) -> 7500 | D23: =IFERROR(D14*$B$22/$B$8,0) -> 7500 | E23: =IFERROR(E14*$B$22/$B$8,0) -> 7500 | F23: =IFERROR(F14*$B$22/$B$8,0) -> 7500 | G23: =IFERROR(G14*$B$22/$B$8,0) -> 7500 | H23: =IFERROR(H14*$B$22/$B$8,0) -> 7500 | I23: =IFERROR(I14*$B$22/$B$8,0) -> 7500 | J23: =IFERROR(J14*$B$22/$B$8,0) -> 7500 | ... N23: =IFERROR(N14*$B$22/$B$8,0) -> 7500
A24: LTV / CAC Ratio | C24: =IFERROR(C23/C21,0) -> 0 | D24: =IFERROR(D23/D21,0) -> 100 | E24: =IFERROR(E23/E21,0) -> 153 | F24: =IFERROR(F23/F21,0) -> 157.5 | G24: =IFERROR(G23/G21,0) -> 112 | H24: =IFERROR(H23/H21,0) -> 65 | I24: =IFERROR(I23/I21,0) -> 116.5 | J24: =IFERROR(J23/J21,0) -> 119.5 | ... N24: =IFERROR(N23/N21,0) -> 131.5
A25: CAC Payback (months) | C25: =IFERROR(C21/(C14*$B$22),0) -> 0 | D25: =IFERROR(D21/(D14*$B$22),0) -> 0.33333333 | E25: =IFERROR(E21/(E14*$B$22),0) -> 0.21786492 | F25: =IFERROR(F21/(F14*$B$22),0) -> 0.21164021 | G25: =IFERROR(G21/(G14*$B$22),0) -> 0.29761905 | H25: =IFERROR(H21/(H14*$B$22),0) -> 0.51282051 | I25: =IFERROR(I21/(I14*$B$22),0) -> 0.28612303 | J25: =IFERROR(J21/(J14*$B$22),0) -> 0.27894003 | ... N25: =IFERROR(N21/(N14*$B$22),0) -> 0.25348542
A27: Health Indicators
A28: Net Revenue Retention (NRR) | B28: 1.05
A29: MRR Growth (annualized) | D29: =IFERROR((D15/C15-1)*12,0) -> 0 | E29: =IFERROR((E15/D15-1)*12,0) -> 30 | F29: =IFERROR((F15/E15-1)*12,0) -> 10.285714 | G29: =IFERROR((G15/F15-1)*12,0) -> 4.6153846 | H29: =IFERROR((H15/G15-1)*12,0) -> 2 | I29: =IFERROR((I15/H15-1)*12,0) -> 1.7142857 | J29: =IFERROR((J15/I15-1)*12,0) -> 2 | K29: =IFERROR((K15/J15-1)*12,0) -> 1.7142857 | ... N29: =IFERROR((N15/M15-1)*12,0) -> 1.2
A30: Cash Balance (end of month) | C30: ='Cash Flow Forecasting'!C33 -> 650 | D30: ='Cash Flow Forecasting'!D33 -> 937 | E30: ='Cash Flow Forecasting'!E33 -> 1604.5 | F30: ='Cash Flow Forecasting'!F33 -> 152.5 | G30: ='Cash Flow Forecasting'!G33 -> -1472.5 | H30: ='Cash Flow Forecasting'!H33 -> 956 | I30: ='Cash Flow Forecasting'!I33 -> -838.5 | J30: ='Cash Flow Forecasting'!J33 -> 2514 | ... N30: ='Cash Flow Forecasting'!N33 -> 11294
A31: Monthly Burn (fixed) | C31: ='Cash Flow Forecasting'!C28 -> 225 | D31: ='Cash Flow Forecasting'!D28 -> 300 | E31: ='Cash Flow Forecasting'!E28 -> 300 | F31: ='Cash Flow Forecasting'!F28 -> 800 | G31: ='Cash Flow Forecasting'!G28 -> 800 | H31: ='Cash Flow Forecasting'!H28 -> 800 | I31: ='Cash Flow Forecasting'!I28 -> 1050 | J31: ='Cash Flow Forecasting'!J28 -> 1050 | ... N31: ='Cash Flow Forecasting'!N28 -> 1050
A32: Months of Runway | C32: =IFERROR(C30/C31,0) -> 2.8888889 | D32: =IFERROR(D30/D31,0) -> 3.1233333 | E32: =IFERROR(E30/E31,0) -> 5.3483333 | F32: =IFERROR(F30/F31,0) -> 0.190625 | G32: =IFERROR(G30/G31,0) -> -1.840625 | H32: =IFERROR(H30/H31,0) -> 1.195 | I32: =IFERROR(I30/I31,0) -> -0.79857143 | J32: =IFERROR(J30/J31,0) -> 2.3942857 | ... N32: =IFERROR(N30/N31,0) -> 10.75619
A34: Legend:
A35: Yellow cells = user inputs (assumptions)
A36: Blue cells = key calculated outputs

Sheet Sensitivity Analysis
A2: Subscription Sales Forecast
A3: Projecting revenue based on current subscription sales and future growth scenarios
A5: Subscription Type | B5: Monitor Price | C5: Sales % | D5: Projected Sales
A6: Small | B6: 250 | C6: 0.05 | D6: =Table58[[#This Row],[Monitor Price]]*(1+Table58[[#This Row],[Sales %]]) -> 262.5
A7: Medium | B7: 300 | C7: 0.03 | D7: =Table58[[#This Row],[Monitor Price]]*(1+Table58[[#This Row],[Sales %]]) -> 309
A8: Large | B8: 350 | C8: 0.02 | D8: =Table58[[#This Row],[Monitor Price]]*(1+Table58[[#This Row],[Sales %]]) -> 357
A9: Total | D9: =SUBTOTAL(109,Table58[Projected Sales]) -> 928.5
A12: Projected Sales by Increase in Sales %
A15: =D6 -> 262.5 | B15: 0.0125 | C15: 0.025 | D15: 0.05 | E15: 0.1
A16: 300 | B16: 303.75 | C16: 307.5 | D16: 315 | E16: 330
A17: 325 | B17: 329.0625 | C17: 333.125 | D17: 341.25 | E17: 357.5
A18: 350 | B18: 354.375 | C18: 358.75 | D18: 367.5 | E18: 385
A19: 375 | B19: 379.6875 | C19: 384.375 | D19: 393.75 | E19: 412.5
A20: 400 | B20: 405 | C20: 410 | D20: 420 | E20: 440
A21: 425 | B21: 430.3125 | C21: 435.625 | D21: 446.25 | E21: 467.5
A23: Insight: Even a modest 2.5% increase in sales volume yields a $25–30 gain per product tier. Targeting a 5–10% growth in high-tier subscriptions could yield disproportionately higher returns.
